starbear/__init__.py
starbear/__main__.py
starbear/common.py
starbear/config.py
starbear/version.py
starbear/assets/bearlib.js
starbear/assets/bearstyle.css
starbear/components/__init__.py
starbear/components/editor.js
starbear/components/editor.py
starbear/core/__init__.py
starbear/core/app.py
starbear/core/constructors.py
starbear/core/page.py
starbear/core/reg.py
starbear/core/repr.py
starbear/core/templating.py
starbear/core/utils.py
starbear/server/__init__.py
starbear/server/config.py
starbear/server/find.py
starbear/server/index.py
starbear/server/misc.py
starbear/server/reload.py
starbear/server/serve.py
starbear/server/plugins/__init__.py
starbear/server/plugins/api_tokens.py
starbear/server/plugins/oauth.py
starbear/server/plugins/permissions.py
starbear/server/plugins/sentry.py
starbear/server/plugins/session.py
starbear/stream/__init__.py
starbear/stream/functions.py
starbear/stream/live.py
starbear/templates/bearlib-template.html
starbear/templates/index-style.css
starbear/templates/index-template.html
starbear/templates/page-template.html
starbear-0.2.10.dist-info/METADATA
starbear-0.2.10.dist-info/WHEEL
starbear-0.2.10.dist-info/entry_points.txt
starbear-0.2.10.dist-info/RECORD
