Metadata-Version: 2.4
Name: starbear
Version: 0.2.10
Summary: Framework for easy small local web apps or programs
Project-URL: Homepage, https://starbear.readthedocs.io/en/latest/
Project-URL: Documentation, https://starbear.readthedocs.io/en/latest/
Project-URL: Repository, https://github.com/breuleux/starbear
Author-email: Olivier Breuleux <breuleux@gmail.com>
License-Expression: MIT
Requires-Python: >=3.11
Requires-Dist: gifnoc~=0.6.2
Requires-Dist: hrepr~=0.9.1
Requires-Dist: lxml>=5.2.2
Requires-Dist: ovld~=0.5.13
Requires-Dist: pyyaml>=6.0.1
Requires-Dist: starlette>=0.38.1
Requires-Dist: websockets>=12.0
Provides-Extra: server
Requires-Dist: authlib>=1.3.1; extra == 'server'
Requires-Dist: httpx>=0.27.0; extra == 'server'
Requires-Dist: itsdangerous>=2.2.0; extra == 'server'
Requires-Dist: jurigged~=0.6.0; extra == 'server'
Requires-Dist: sse-starlette<3.0.0,>=2.1.2; extra == 'server'
Requires-Dist: uvicorn>=0.30.3; extra == 'server'
Requires-Dist: watchdog>=4.0.1; extra == 'server'
